st_highlightable_text/__init__.py
st_highlightable_text/frontend/build/asset-manifest.json
st_highlightable_text/frontend/build/index.html
st_highlightable_text/frontend/build/static/css/2.da08aea5.chunk.css
st_highlightable_text/frontend/build/static/css/2.da08aea5.chunk.css.map
st_highlightable_text/frontend/build/static/js/2.161055fe.chunk.js
st_highlightable_text/frontend/build/static/js/2.161055fe.chunk.js.LICENSE.txt
st_highlightable_text/frontend/build/static/js/2.161055fe.chunk.js.map
st_highlightable_text/frontend/build/static/js/main.24fde773.chunk.js
st_highlightable_text/frontend/build/static/js/main.24fde773.chunk.js.map
st_highlightable_text/frontend/build/static/js/runtime-main.d8107819.js
st_highlightable_text/frontend/build/static/js/runtime-main.d8107819.js.map
st_highlightable_text-0.1.0.dist-info/LICENSE
st_highlightable_text-0.1.0.dist-info/METADATA
st_highlightable_text-0.1.0.dist-info/WHEEL
st_highlightable_text-0.1.0.dist-info/top_level.txt
st_highlightable_text-0.1.0.dist-info/RECORD
