Metadata-Version: 2.1
Name: st-highlightable-text
Version: 0.1.0
Summary: Highlightable text for data labelling.
Home-page: UNKNOWN
Author: Theo Stosse
Author-email: tstosse@advaes.com
License: UNKNOWN
Platform: UNKNOWN
Requires-Python: >=3.6
License-File: LICENSE
Requires-Dist: streamlit (>=1.1)
